defect_megareport/__init__.py
defect_megareport/filters.py
defect_megareport/models.py
defect_megareport/raw_sql.py
defect_megareport/selectors.py
defect_megareport/serializers.py
defect_megareport/tasks.py
defect_megareport/urls.py
defect_megareport/views.py
defect_megareport/migrations/0001_initial.py
defect_megareport/migrations/__init__.py
defect_megareport/static/defect_report/css/bootstrap.min.css
defect_megareport/static/defect_report/css/defect_report.css
defect_megareport/static/defect_report/js/bootstrap.min.js
defect_megareport/static/defect_report/js/defect_report.js
defect_megareport/static/defect_report/js/jquery-3.5.1.slim.min.js
defect_megareport/static/defect_report/js/popper.min.js
defect_megareport/templates/defect_report_page.html
defect_megareport-0.0.2.dist-info/METADATA
defect_megareport-0.0.2.dist-info/WHEEL
defect_megareport-0.0.2.dist-info/entry_points.txt
defect_megareport-0.0.2.dist-info/top_level.txt
defect_megareport-0.0.2.dist-info/RECORD
