Metadata-Version: 2.4
Name: defect-megareport
Version: 0.0.2
Summary: defect megareport
Author-email: Ivan Dorodnitsyn <ivdorodnitsyn@gmail.com>
Project-URL: Homepage, https://github.com/evildarius/defect-megareport
Classifier: Programming Language :: Python :: 3
Classifier: License :: OSI Approved :: MIT License
Classifier: Operating System :: OS Independent
Requires-Python: >=3.11
Requires-Dist: requests>=2.28.0
